mcp_server_danchoicloud/__init__.py
mcp_server_danchoicloud/__main__.py
mcp_server_danchoicloud/server.py
mcp_server_danchoicloud/tools/__init__.py
mcp_server_danchoicloud/tools/sieu_nhan.py
mcp_server_danchoicloud-0.1.0.dist-info/METADATA
mcp_server_danchoicloud-0.1.0.dist-info/WHEEL
mcp_server_danchoicloud-0.1.0.dist-info/entry_points.txt
mcp_server_danchoicloud-0.1.0.dist-info/licenses/LICENSE
mcp_server_danchoicloud-0.1.0.dist-info/RECORD
