Metadata-Version: 2.4
Name: mcp-server-danchoicloud
Version: 0.1.0
Summary: Add your description here
Author-email: hoangndst <hoangndst@gmail.com>
License: MIT
License-File: LICENSE
Keywords: llm,mcp
Classifier: Development Status :: 4 - Beta
Classifier: Intended Audience :: Developers
Classifier: License :: OSI Approved :: MIT License
Classifier: Programming Language :: Python :: 3
Classifier: Programming Language :: Python :: 3.12
Requires-Python: >=3.12
Requires-Dist: httpx>=0.28.1
Requires-Dist: mcp[cli]>=1.6.0
